limier/__init__.py
limier/aliases.py
limier/converters.py
limier/decorators.py
limier/exceptions.py
limier/registry.py
limier/typevars.py
limier-0.0.2.dist-info/LICENSE
limier-0.0.2.dist-info/METADATA
limier-0.0.2.dist-info/WHEEL
limier-0.0.2.dist-info/top_level.txt
limier-0.0.2.dist-info/RECORD
