Metadata-Version: 2.1
Name: limier
Version: 0.0.2
Summary: Smart toolkit for conversion and validation of function arguments powered by type annotations
Home-page: https://github.com/florimondmanca/limier
Author: Florimond Manca
Author-email: florimond.manca@gmail.com
License: License :: OSI Approved :: MIT License
Platform: UNKNOWN
Classifier: Operating System :: OS Independent
Classifier: License :: OSI Approved :: MIT License
Classifier: Programming Language :: Python
Classifier: Programming Language :: Python :: 3.6
Classifier: Programming Language :: Python :: 3.7
Requires-Python: >=3.6
